Metadata-Version: 2.1
Name: Ezalt
Version: 0.1.1
Summary: Programa baseado na planilha Ezalt de Richard Nakka para cálculo de uma estimativa de performance de voo. Program based on Richard Nakka spreadsheet for flight performance estimator
Home-page: https://github.com/LucasValentimB/Ezalt
Author: Lucas Valentim Câmara
Author-email: lucasbcamara@gmail.com
License: UNKNOWN
Keywords: Ezalt,foguete,Performance,voo,melhor massa,Nakka,burnout
Platform: UNKNOWN
Classifier: Development Status :: 4 - Beta
Classifier: Intended Audience :: Developers
Classifier: Intended Audience :: Other Audience
Classifier: Topic :: Software Development :: Build Tools
Classifier: Topic :: Scientific/Engineering
Classifier: Topic :: Scientific/Engineering :: Physics
Classifier: License :: OSI Approved :: MIT License
Classifier: Programming Language :: Python :: 3
Classifier: Programming Language :: Python :: 3.6
Classifier: Programming Language :: Python :: 3.7
Classifier: Programming Language :: Python :: 3.8
Classifier: Programming Language :: Python :: 3.9
Classifier: Programming Language :: Python :: 3 :: Only
Requires-Python: >=3.6, <4
Provides-Extra: dev
Provides-Extra: test
